README.rst
setup.py
djeese/__init__.py
djeese/apps.py
djeese/boilerplates.py
djeese/errorcodes.py
djeese/input_helpers.py
djeese/printer.py
djeese/serializer.py
djeese/smartconfig.py
djeese/utils.py
djeese.egg-info/PKG-INFO
djeese.egg-info/SOURCES.txt
djeese.egg-info/dependency_links.txt
djeese.egg-info/entry_points.txt
djeese.egg-info/requires.txt
djeese.egg-info/top_level.txt
djeese/commands/__init__.py
djeese/commands/checkapp.py
djeese/commands/checkboilerplate.py
djeese/commands/clonestatic.py
djeese/commands/createapp.py
djeese/commands/createboilerplate.py
djeese/commands/pushstatic.py
djeese/commands/runstatic.py
djeese/commands/uploadapp.py
djeese/commands/uploadboilerplate.py