Metadata-Version: 1.0
Name: djeese
Version: 0.6.1
Summary: The command-line client for the djee.se service
Home-page: http://djeese.com/
Author: The djee.se Team
Author-email: say@djee.se
License: LICENSE.txt
Platform: OS Independent
